pyetfdb_scraper/__init__.py
pyetfdb_scraper/etf.py
pyetfdb_scraper/etf_scraper.py
pyetfdb_scraper/utils.py
pyetfdb_scraper/data/etfdb.json
pyetfdb_scraper/data/user-agents.txt
pyetfdb_scraper/models/__init__.py
pyetfdb_scraper/models/expense.py
pyetfdb_scraper/models/info.py
pyetfdb_scraper/tabs/__init__.py
pyetfdb_scraper/tabs/dividend.py
pyetfdb_scraper/tabs/expense.py
pyetfdb_scraper/tabs/holding_analysis.py
pyetfdb_scraper/tabs/holdings.py
pyetfdb_scraper/tabs/info.py
pyetfdb_scraper/tabs/performance.py
pyetfdb_scraper/tabs/realtime_ratings.py
pyetfdb_scraper/tabs/technicals.py
pyetfdb_scraper-0.4.dist-info/LICENSE
pyetfdb_scraper-0.4.dist-info/METADATA
pyetfdb_scraper-0.4.dist-info/WHEEL
pyetfdb_scraper-0.4.dist-info/top_level.txt
pyetfdb_scraper-0.4.dist-info/RECORD
