Metadata-Version: 2.1
Name: pyetfdb_scraper
Version: 0.4
Summary: Scrape ETFs from ETFDB
Home-page: https://github.com/lvxhnat/pyetf-scraper
Author: Yi Kuang
Author-email: yikuang5@gmail.com
Requires-Python: >=3.7
Provides-Extra: dev
License-File: LICENSE
